Metadata-Version: 2.1
Name: example-pkg-ReidTaylor929
Version: 0.0.1
Summary: A small project
Home-page: https://github.com/pypa/sampleproject
Author: Reid Taylor
Author-email: Rebridgers@gmail.com
License: UNKNOWN
Platform: UNKNOWN
Classifier: Programming Language :: Python :: 3
Classifier: License :: OSI Approved :: MIT License
Classifier: Operating System :: OS Independent
Requires-Python: >=3.6
